<x:xmpmeta tsc:version="2.0.1" xmlns:x="adobe:ns:meta/" xmlns:tsc="http://www.techsmith.com/xmp/tsc/">
   <rdf:RDF xmlns:rdf="http://www.w3.org/1999/02/22-rdf-syntax-ns#" xmlns:xmp="http://ns.adobe.com/xap/1.0/" xmlns:xmpDM="http://ns.adobe.com/xmp/1.0/DynamicMedia/" xmlns:xmpG="http://ns.adobe.com/xap/1.0/g/" xmlns:xmpMM="http://ns.adobe.com/xap/1.0/mm/" xmlns:tscDM="http://www.techsmith.com/xmp/tscDM/" xmlns:tscIQ="http://www.techsmith.com/xmp/tscIQ/" xmlns:tscHS="http://www.techsmith.com/xmp/tscHS/" xmlns:stDim="http://ns.adobe.com/xap/1.0/sType/Dimensions#" xmlns:stFnt="http://ns.adobe.com/xap/1.0/sType/Font#" xmlns:exif="http://ns.adobe.com/exif/1.0" xmlns:dc="http://purl.org/dc/elements/1.1/">
      <rdf:Description dc:date="2020-07-14 12:55:38 PM" dc:source="Camtasia,19.0.1,enu" dc:title="MATH7_5.2Q10" tscDM:firstFrame="MATH7_5.2Q10_First_Frame.png" tscDM:originId="F56763D3-C5D1-469F-9397-32BFC2F2FB7E" tscDM:project="MATH7_5.2Q10">
         <xmpDM:duration xmpDM:scale="1/1000" xmpDM:value="399600"/>
         <xmpDM:videoFrameSize stDim:unit="pixel" stDim:h="1080" stDim:w="1920"/>
         <tsc:langName>
            <rdf:Bag>
               <rdf:li xml:lang="en-US">English</rdf:li></rdf:Bag>
         </tsc:langName>
         <xmpDM:Tracks>
            <rdf:Bag>
               <rdf:li>
                  <rdf:Description xmpDM:trackType="Hotspot" xmpDM:frameRate="f1000" xmpDM:trackName="Hotspots">
                     <xmpDM:markers>
                        <rdf:Seq>
                           <rdf:li><rdf:Description xmpDM:label="1" xmpDM:startTime="5330" xmpDM:duration="19370" tscDM:boundingPoly="172,496;365,496;365,617;172,617;" tscDM:rotate="0.000000" tscHS:pause="0" tscHS:jumpTime="3733"/></rdf:li><rdf:li><rdf:Description xmpDM:label="2" xmpDM:startTime="25700" xmpDM:duration="226430" tscDM:boundingPoly="172,258;365,258;365,379;172,379;" tscDM:rotate="0.000000" tscHS:pause="0" tscHS:jumpTime="3733"/></rdf:li><rdf:li><rdf:Description xmpDM:label="3" xmpDM:startTime="253130" xmpDM:duration="138570" tscDM:boundingPoly="172,42;365,42;365,163;172,163;" tscDM:rotate="0.000000" tscHS:pause="0" tscHS:jumpTime="3733"/></rdf:li><rdf:li><rdf:Description xmpDM:label="4" xmpDM:startTime="393270" xmpDM:duration="5330" tscDM:boundingPoly="260,324;453,324;453,445;260,445;" tscDM:rotate="0.000000" tscHS:pause="1" tscHS:jumpTime="3733"/></rdf:li><rdf:li><rdf:Description xmpDM:label="5" xmpDM:startTime="5900" xmpDM:duration="18800" tscDM:boundingPoly="412,484;1228,484;1228,575;412,575;" tscDM:rotate="0.000000" tscHS:pause="0" tscHS:jumpTime="5600"/></rdf:li><rdf:li><rdf:Description xmpDM:label="6" xmpDM:startTime="25700" xmpDM:duration="226430" tscDM:boundingPoly="412,246;1228,246;1228,337;412,337;" tscDM:rotate="0.000000" tscHS:pause="0" tscHS:jumpTime="5600"/></rdf:li><rdf:li><rdf:Description xmpDM:label="7" xmpDM:startTime="253130" xmpDM:duration="138570" tscDM:boundingPoly="412,30;1228,30;1228,121;412,121;" tscDM:rotate="0.000000" tscHS:pause="0" tscHS:jumpTime="5600"/></rdf:li><rdf:li><rdf:Description xmpDM:label="8" xmpDM:startTime="393270" xmpDM:duration="5330" tscDM:boundingPoly="500,312;1316,312;1316,403;500,403;" tscDM:rotate="0.000000" tscHS:pause="1" tscHS:jumpTime="5600"/></rdf:li><rdf:li><rdf:Description xmpDM:label="9" xmpDM:startTime="25600" xmpDM:duration="226570" tscDM:boundingPoly="152,498;465,498;465,614;152,614;" tscDM:rotate="0.000000" tscHS:pause="0" tscHS:jumpTime="25267"/></rdf:li><rdf:li><rdf:Description xmpDM:label="10" xmpDM:startTime="253170" xmpDM:duration="138530" tscDM:boundingPoly="152,281;465,281;465,397;152,397;" tscDM:rotate="0.000000" tscHS:pause="0" tscHS:jumpTime="25267"/></rdf:li><rdf:li><rdf:Description xmpDM:label="11" xmpDM:startTime="393270" xmpDM:duration="5330" tscDM:boundingPoly="240,564;553,564;553,680;240,680;" tscDM:rotate="0.000000" tscHS:pause="1" tscHS:jumpTime="25267"/></rdf:li><rdf:li><rdf:Description xmpDM:label="12" xmpDM:startTime="82530" xmpDM:duration="148700" tscDM:boundingPoly="1550,723;1859,723;1859,821;1550,821;" tscDM:rotate="0.000000" tscHS:pause="1" tscHS:jumpTime="82467"/></rdf:li><rdf:li><rdf:Description xmpDM:label="13" xmpDM:startTime="131730" xmpDM:duration="120440" tscDM:boundingPoly="412,649;487,649;487,733;412,733;" tscDM:rotate="0.000000" tscHS:pause="0" tscHS:jumpTime="131067"/></rdf:li><rdf:li><rdf:Description xmpDM:label="14" xmpDM:startTime="253170" xmpDM:duration="138260" tscDM:boundingPoly="412,387;487,387;487,471;412,471;" tscDM:rotate="0.000000" tscHS:pause="1" tscHS:jumpTime="131067"/></rdf:li><rdf:li><rdf:Description xmpDM:label="15" xmpDM:startTime="207730" xmpDM:duration="44440" tscDM:boundingPoly="412,813;487,813;487,897;412,897;" tscDM:rotate="0.000000" tscHS:pause="0" tscHS:jumpTime="207433"/></rdf:li><rdf:li><rdf:Description xmpDM:label="16" xmpDM:startTime="253170" xmpDM:duration="138260" tscDM:boundingPoly="412,507;487,507;487,591;412,591;" tscDM:rotate="0.000000" tscHS:pause="1" tscHS:jumpTime="207433"/></rdf:li><rdf:li><rdf:Description xmpDM:label="17" xmpDM:startTime="258870" xmpDM:duration="132560" tscDM:boundingPoly="412,645;487,645;487,729;412,729;" tscDM:rotate="0.000000" tscHS:pause="1" tscHS:jumpTime="259500"/></rdf:li><rdf:li><rdf:Description xmpDM:label="18" xmpDM:startTime="303970" xmpDM:duration="87460" tscDM:boundingPoly="410,754;485,754;485,838;410,838;" tscDM:rotate="0.000000" tscHS:pause="1" tscHS:jumpTime="304800"/></rdf:li><rdf:li><rdf:Description xmpDM:label="19" xmpDM:startTime="345930" xmpDM:duration="45500" tscDM:boundingPoly="412,866;487,866;487,950;412,950;" tscDM:rotate="0.000000" tscHS:pause="1" tscHS:jumpTime="346833"/></rdf:li><rdf:li><rdf:Description xmpDM:label="20" xmpDM:startTime="382930" xmpDM:duration="8770" tscDM:boundingPoly="397,932;789,932;789,1047;397,1047;" tscDM:rotate="0.000000" tscHS:pause="1" tscHS:jumpTime="381167"/></rdf:li></rdf:Seq>
                     </xmpDM:markers>
                  </rdf:Description>
               </rdf:li>
            </rdf:Bag>
         </xmpDM:Tracks>
         <tscDM:controller>
            <rdf:Description xmpDM:name="tscplayer">
               <tscDM:parameters>
                  <rdf:Bag>
                     <rdf:li xmpDM:name="autohide" xmpDM:value="true"/><rdf:li xmpDM:name="autoplay" xmpDM:value="false"/><rdf:li xmpDM:name="loop" xmpDM:value="true"/><rdf:li xmpDM:name="searchable" xmpDM:value="false"/><rdf:li xmpDM:name="captionsenabled" xmpDM:value="false"/><rdf:li xmpDM:name="sidebarenabled" xmpDM:value="false"/><rdf:li xmpDM:name="unicodeenabled" xmpDM:value="false"/><rdf:li xmpDM:name="backgroundcolor" xmpDM:value="1E1C1C"/><rdf:li xmpDM:name="sidebarlocation" xmpDM:value="left"/><rdf:li xmpDM:name="endaction" xmpDM:value="loop"/><rdf:li xmpDM:name="endactionparam" xmpDM:value="true"/><rdf:li xmpDM:name="locale" xmpDM:value="en-US"/></rdf:Bag>
               </tscDM:parameters>
               <tscDM:controllerText>
                  <rdf:Bag>
                  </rdf:Bag>
               </tscDM:controllerText>
            </rdf:Description>
         </tscDM:controller>
         <tscDM:contentList>
            <rdf:Description>
               <tscDM:files>
                  <rdf:Seq>
                     <rdf:li xmpDM:name="0" xmpDM:value="MATH7_5.2Q10.mp4"/><rdf:li xmpDM:name="1" xmpDM:value="MATH7_5.2Q10_First_Frame.png"/></rdf:Seq>
               </tscDM:files>
            </rdf:Description>
         </tscDM:contentList>
      </rdf:Description>
   </rdf:RDF>
</x:xmpmeta>